{"cameraMode":{"drawMode":0,"name":"Shaded","section":"Shading Mode"},"sceneLighting":true,"audioPlay":false,"sceneViewState":{"m_AlwaysRefresh":false,"showFog":true,"showSkybox":true,"showFlares":true,"showImageEffects":true,"showParticleSystems":true,"showVisualEffectGraphs":true,"m_FxEnabled":true},"in2DMode":false,"pivot":{"x":1.6878281831741334,"y":1.9012386798858643,"z":-0.010986328125},"rotation":{"x":-0.0056715672835707668,"y":-0.010494133457541466,"z":-0.0018555019050836564,"w":1.0001338720321656},"size":1.2702187299728394,"orthographic":false}